mikrocad/__init__.py
mikrocad/experiment.py
mikrocad/fd3.py
mikrocad/mikrocad.py
mikrocad/mikrocad_mock.py
mikrocad/parameter.py
mikrocad/sample.py
mikrocad/widgets/__init__.py
mikrocad/widgets/microcad_measurebox.py
mikrocad/widgets/mikrocad_live.py
mikrocad/widgets/mikrocad_mainwindow.py
mikrocad/widgets/mikrocad_sequencer_widget.py
mikrocad-0.0.7.dist-info/METADATA
mikrocad-0.0.7.dist-info/RECORD
mikrocad-0.0.7.dist-info/WHEEL
mikrocad-0.0.7.dist-info/top_level.txt
tests/__init__.py
tests/test_00_fd3.py
tests/test_01_mikrocad.py
tests/test_02_mikrocad_live.py
tests/test_03_mikrocad_live_mock_up.py
tests/test_10_mikrocad_threaded.py
tests/test_11_mikrocad_mock_up.py
tests/test_12_mikrocad_errors.py
usage/__init__.py
usage/use_00_mikrocad.py
usage/use_01_mikrocad_parameters.py
usage/use_02_mikrocad_camera.py
usage/use_02_mikrocad_camera_brightness.py
usage/use_03_mikrocad_measurement.py
usage/use_04_mikrocad_threaded.py
usage/use_05_mikrocad_camera_justage.py
usage/use_10_mikrocad_zmq_server.py
usage/use_11_mikrocad_zmq_client_json.py
usage/use_20_mikrocad_live_widget.py
usage/use_21_handle_to_live_widget.py
usage/use_21_mikrocad_live_widget_mock_up.py
usage/use_22_mikrocad_live_image.py
usage/use_30_mikrocad_mainwindow.py
usage/use_99_handle_to_live_widget.py
usage/use_experiment.py
