Metadata-Version: 2.1
Name: mikrocad
Version: 0.0.7
Summary: LMI GFM FD3 filereader
Home-page: https://bitbucket.org/hirschbeutel/mikrocad
Author: hirschbeutel
Author-email: hirschbeutel@gmail.com
License: MIT
Platform: UNKNOWN
Classifier: Programming Language :: Python :: 3
Classifier: Programming Language :: Python :: 3.5
Classifier: Programming Language :: Python :: 3.6
